xmlstreamparser/__init__.py
xmlstreamparser/handlers.py
PyXMLStreamParser-0.1.2.dist-info/LICENSE
PyXMLStreamParser-0.1.2.dist-info/METADATA
PyXMLStreamParser-0.1.2.dist-info/WHEEL
PyXMLStreamParser-0.1.2.dist-info/top_level.txt
PyXMLStreamParser-0.1.2.dist-info/zip-safe
PyXMLStreamParser-0.1.2.dist-info/RECORD
